keras_batchflow/__init__.py
keras_batchflow/base/__init__.py
keras_batchflow/base/batch_generators/__init__.py
keras_batchflow/base/batch_generators/batch_generator.py
keras_batchflow/base/batch_generators/triplet_pk_generator.py
keras_batchflow/base/batch_shapers/__init__.py
keras_batchflow/base/batch_shapers/batch_shaper.py
keras_batchflow/base/batch_shapers/encoder_adaptor.py
keras_batchflow/base/batch_shapers/numpy_encoder_adaptor.py
keras_batchflow/base/batch_shapers/pandas_encoder_adaptor.py
keras_batchflow/base/batch_shapers/var_shaper.py
keras_batchflow/base/batch_transformers/__init__.py
keras_batchflow/base/batch_transformers/base_random_cell.py
keras_batchflow/base/batch_transformers/batch_fork.py
keras_batchflow/base/batch_transformers/batch_transformer.py
keras_batchflow/base/batch_transformers/feature_dropout.py
keras_batchflow/base/batch_transformers/shuffle_noise.py
keras_batchflow/base/encoders/__init__.py
keras_batchflow/base/encoders/base_encoder.py
keras_batchflow/base/encoders/identity_encoder.py
keras_batchflow/keras/__init__.py
keras_batchflow/keras/batch_generators/__init__.py
keras_batchflow/keras/batch_generators/batch_generator.py
keras_batchflow/keras/batch_generators/triplet_pk_generator.py
keras_batchflow/keras/batch_shapers/__init__.py
keras_batchflow/keras/batch_transformers/__init__.py
keras_batchflow/keras/encoders/__init__.py
keras_batchflow/tf/__init__.py
keras_batchflow/tf/batch_generators/__init__.py
keras_batchflow/tf/batch_generators/batch_generator.py
keras_batchflow/tf/batch_generators/triplet_pk_generator.py
keras_batchflow/tf/batch_shapers/__init__.py
keras_batchflow/tf/batch_transformers/__init__.py
keras_batchflow/tf/encoders/__init__.py
keras_batchflow-0.1.8.dist-info/LICENSE
keras_batchflow-0.1.8.dist-info/METADATA
keras_batchflow-0.1.8.dist-info/WHEEL
keras_batchflow-0.1.8.dist-info/top_level.txt
keras_batchflow-0.1.8.dist-info/RECORD
